sphinxcontrib_commonmark-0.1.0-py3.7-nspkg.pth
sphinxcontrib/commonmark/__init__.py
sphinxcontrib/commonmark/version.py
sphinxcontrib_commonmark-0.1.0.dist-info/LICENSE
sphinxcontrib_commonmark-0.1.0.dist-info/METADATA
sphinxcontrib_commonmark-0.1.0.dist-info/WHEEL
sphinxcontrib_commonmark-0.1.0.dist-info/namespace_packages.txt
sphinxcontrib_commonmark-0.1.0.dist-info/top_level.txt
sphinxcontrib_commonmark-0.1.0.dist-info/RECORD
