Metadata-Version: 2.1
Name: sphinxcontrib-commonmark
Version: 0.1.0
Summary: Yet another commonmark processor for Sphinx
Home-page: https://github.com/tk0miya/sphinxcontrib-commonmark/
Author: Takeshi KOMIYA
Author-email: i.tkomiya@gmail.com
License: UNKNOWN
Platform: UNKNOWN
Classifier: Development Status :: 3 - Alpha
Classifier: Environment :: Console
Classifier: Framework :: Sphinx :: Extension
Classifier: Intended Audience :: Developers
Classifier: License :: OSI Approved :: Apache Software License
Classifier: Operating System :: OS Independent
Classifier: Programming Language :: Python
Classifier: Programming Language :: Python :: 3.7
Classifier: Topic :: Documentation
Classifier: Topic :: Documentation :: Sphinx
Classifier: Topic :: Utilities
Requires-Dist: Sphinx (>=2.0)
Requires-Dist: pycmark
Provides-Extra: test
Requires-Dist: tox ; extra == 'test'
Requires-Dist: flake8 ; extra == 'test'
Requires-Dist: flake8-import-order ; extra == 'test'
Requires-Dist: pytest ; extra == 'test'
Requires-Dist: mypy ; extra == 'test'
